reqdriver/__init__.py
reqdriver/main.py
reqdriver-0.1.2.dist-info/LICENSE
reqdriver-0.1.2.dist-info/METADATA
reqdriver-0.1.2.dist-info/WHEEL
reqdriver-0.1.2.dist-info/top_level.txt
reqdriver-0.1.2.dist-info/RECORD
