Metadata-Version: 2.1
Name: reqdriver
Version: 0.1.2
Summary: Effortlessly transfer sessions from Python requests to Selenium WebDriver.
Home-page: https://github.com/glizzykingdreko/reqdriver
Author: glizzykingdreko
Author-email: glizzykingdreko@protonmail.com
Keywords: web scraping browser automation selenium webdriver python requests session transfer automated testing web automation selenium browser http requests cookie management proxy handling selenium sessions web testing data scraping selenium cookies
Classifier: Development Status :: 3 - Alpha
Classifier: Intended Audience :: Developers
Classifier: License :: OSI Approved :: MIT License
Classifier: Programming Language :: Python :: 3
Classifier: Programming Language :: Python :: 3.8
Classifier: Programming Language :: Python :: 3.9
Classifier: Programming Language :: Python :: 3.10
License-File: LICENSE
Requires-Dist: selenium >=3.141.0
Requires-Dist: requests >=2.25.1
